precision_lasso/VariableSelection.py
precision_lasso/__init__.py
precision_lasso/helpingMethods.py
precision_lasso-0.2.dist-info/LICENSE.txt
precision_lasso-0.2.dist-info/METADATA
precision_lasso-0.2.dist-info/WHEEL
precision_lasso-0.2.dist-info/top_level.txt
precision_lasso-0.2.dist-info/RECORD
