Metadata-Version: 2.1
Name: precision-lasso
Version: 0.2
Summary: An implementation of Precision Lasso, a statistical model that promotes sparse variable selection in the presence of correlated and linearly dependent variables. 
Home-page: https://github.com/Liu-Hy/precision-lasso
Author: Haohan Wang
Author-email: haohanw@illinois.edu
License: LICENSE.txt
Keywords: regression,variable-selection
License-File: LICENSE.txt
Requires-Dist: scipy
Requires-Dist: numpy
